MANIFEST.in
setup.py
stb_tester.egg-info/PKG-INFO
stb_tester.egg-info/SOURCES.txt
stb_tester.egg-info/dependency_links.txt
stb_tester.egg-info/requires.txt
stb_tester.egg-info/top_level.txt
stbt/__init__.py
stbt/audio.py
stbt/prometheus.py
stbt/pylint_plugin.py