Metadata-Version: 2.1
Name: stb-tester
Version: 34.10.0
Summary: Automated GUI testing for Set-Top Boxes
Home-page: https://stb-tester.com
Author: Stb-tester.com Ltd.
Author-email: support@stb-tester.com
License: UNKNOWN
Platform: UNKNOWN
Classifier: Development Status :: 5 - Production/Stable
Classifier: Operating System :: OS Independent
Classifier: Programming Language :: Python :: 3.10
Classifier: Topic :: Software Development :: Testing
Requires-Python: >=3.10
